gh_stats/__init__.py
gh_stats/cli.py
github_repo_stats-0.1.2.dist-info/entry_points.txt
github_repo_stats-0.1.2.dist-info/LICENSE
github_repo_stats-0.1.2.dist-info/WHEEL
github_repo_stats-0.1.2.dist-info/METADATA
github_repo_stats-0.1.2.dist-info/RECORD
