Metadata-Version: 2.1
Name: github_repo_stats
Version: 0.1.2
Summary: Fetch your GH Repo stats
Author-email: Ricky White <ricky@migusgroup.com>
Requires-Python: >=3.7
Classifier: License :: OSI Approved :: MIT License
Classifier: Programming Language :: Python :: 3.7
Classifier: Programming Language :: Python :: 3.8
Classifier: Programming Language :: Python :: 3.9
Classifier: Programming Language :: Python :: 3.10
Requires-Dist: pyyaml==6.0
Requires-Dist: requests==2.28.1
Requires-Dist: click==8.1.3
Requires-Dist: rich==12.5.1
Project-URL: Home, https://migusgroup.com
Project-URL: Source, https://github.com/The-Migus-Group/gh-repo-stats
